pymongocrypt/__init__.py
pymongocrypt/auto_encrypter.py
pymongocrypt/binary.py
pymongocrypt/binding.py
pymongocrypt/compat.py
pymongocrypt/credentials.py
pymongocrypt/crypto.py
pymongocrypt/errors.py
pymongocrypt/explicit_encrypter.py
pymongocrypt/mongocrypt.py
pymongocrypt/options.py
pymongocrypt/state_machine.py
pymongocrypt/version.py
pymongocrypt/asynchronous/auto_encrypter.py
pymongocrypt/asynchronous/credentials.py
pymongocrypt/asynchronous/explicit_encrypter.py
pymongocrypt/asynchronous/state_machine.py
pymongocrypt/synchronous/auto_encrypter.py
pymongocrypt/synchronous/credentials.py
pymongocrypt/synchronous/explicit_encrypter.py
pymongocrypt/synchronous/state_machine.py
pymongocrypt/mongocrypt.dll
pymongocrypt-1.16.0.dist-info/METADATA
pymongocrypt-1.16.0.dist-info/WHEEL
pymongocrypt-1.16.0.dist-info/licenses/LICENSE
pymongocrypt-1.16.0.dist-info/RECORD
