Metadata-Version: 2.4
Name: pymongocrypt
Version: 1.16.0
Summary: Python bindings for libmongocrypt
Project-URL: Homepage, https://github.com/mongodb/libmongocrypt/tree/master/bindings/python
Author-email: Shane Harvey <mongodb-user@googlegroups.com>
License:                                  Apache License
License-File: LICENSE
Keywords: bson,mongo,mongocrypt,mongodb,pymongo,pymongocrypt
Classifier: Development Status :: 5 - Production/Stable
Classifier: Intended Audience :: Developers
Classifier: License :: OSI Approved :: Apache Software License
Classifier: Operating System :: MacOS :: MacOS X
Classifier: Operating System :: Microsoft :: Windows
Classifier: Operating System :: POSIX
Classifier: Programming Language :: Python :: 3
Classifier: Programming Language :: Python :: 3 :: Only
Classifier: Programming Language :: Python :: 3.9
Classifier: Programming Language :: Python :: 3.10
Classifier: Programming Language :: Python :: 3.11
Classifier: Programming Language :: Python :: 3.12
Classifier: Programming Language :: Python :: 3.13
Classifier: Programming Language :: Python :: 3.14
Classifier: Programming Language :: Python :: Implementation :: CPython
Classifier: Programming Language :: Python :: Implementation :: PyPy
Classifier: Topic :: Database
Requires-Python: >=3.9
Requires-Dist: cffi<3,>=1.12.0
Requires-Dist: cryptography>=40
Requires-Dist: httpx>=0.25.0
Requires-Dist: packaging>=21.0
Provides-Extra: test
Requires-Dist: cffi<2,>=1.12.0; extra == 'test'
Requires-Dist: cryptography>=2; extra == 'test'
Requires-Dist: pymongo[aws]>=4; extra == 'test'
Requires-Dist: pytest>=7.0; extra == 'test'
Requires-Dist: respx; extra == 'test'
Requires-Dist: setuptools; extra == 'test'
Requires-Dist: unasync; extra == 'test'
